discord/ext/ipc/__init__.py
discord/ext/ipc/client.py
discord/ext/ipc/errors.py
discord/ext/ipc/server.py
discord_ext_ipc-2.1.1.dist-info/LICENSE
discord_ext_ipc-2.1.1.dist-info/METADATA
discord_ext_ipc-2.1.1.dist-info/WHEEL
discord_ext_ipc-2.1.1.dist-info/top_level.txt
discord_ext_ipc-2.1.1.dist-info/RECORD
