Metadata-Version: 2.1
Name: discord-ext-ipc
Version: 2.1.1
Summary: A discord.py extension for inter-process communication.
Home-page: https://github.com/Ext-Creators/discord-ext-ipc
Author: Ext-Creators
License: Apache Software License
Project-URL: Documentation, https://discord-ext-ipc.readthedocs.io
Project-URL: Issue Tracker, https://github.com/Ext-Creators/discord-ext-ipc/issues
Project-URL: Source, https://github.com/Ext-Creators/discord-ext-ipc
Platform: UNKNOWN
Classifier: Development Status :: 5 - Production/Stable
Classifier: Framework :: AsyncIO
Classifier: Intended Audience :: Developers
Classifier: License :: OSI Approved :: Apache Software License
Classifier: Natural Language :: English
Classifier: Operating System :: OS Independent
Classifier: Programming Language :: Python
Classifier: Programming Language :: Python :: 3
Classifier: Programming Language :: Python :: 3 :: Only
Classifier: Programming Language :: Python :: 3.5
Classifier: Programming Language :: Python :: 3.6
Classifier: Programming Language :: Python :: 3.7
Classifier: Programming Language :: Python :: 3.8
Classifier: Programming Language :: Python :: 3.9
Classifier: Programming Language :: Python :: 3.10
Classifier: Programming Language :: Python :: Implementation :: CPython
Classifier: Topic :: Communications
Classifier: Topic :: Documentation
Classifier: Topic :: Documentation :: Sphinx
Classifier: Topic :: Internet
Classifier: Topic :: Software Development
Classifier: Topic :: Software Development :: Libraries
Classifier: Topic :: Software Development :: Libraries :: Python Modules
Requires-Python: >=3.5.3
Provides-Extra: docs
License-File: LICENSE
